django_rest_kegg/__init__.py
django_rest_kegg/admin.py
django_rest_kegg/apps.py
django_rest_kegg/models.py
django_rest_kegg/tests.py
django_rest_kegg/urls.py
django_rest_kegg/utils.py
django_rest_kegg/views.py
django_rest_kegg/management/__init__.py
django_rest_kegg/management/commands/__init__.py
django_rest_kegg/management/commands/build.py
django_rest_kegg/migrations/__init__.py
django_rest_kegg/version/version.json
django_rest_kegg-1.0.7.dist-info/METADATA
django_rest_kegg-1.0.7.dist-info/WHEEL
django_rest_kegg-1.0.7.dist-info/top_level.txt
django_rest_kegg-1.0.7.dist-info/RECORD
