Metadata-Version: 2.1
Name: django-rest-kegg
Version: 1.0.7
Summary: an application of kegg pathway for django rest framework
Home-page: https://github.com/suqingdong/django_rest_kegg
Author: suqingdong
Author-email: suqingdong1114@gmail.com
License: BSD License
Platform: UNKNOWN
Classifier: Framework :: Django
Classifier: Framework :: Django :: 3.2
Classifier: Operating System :: OS Independent
Classifier: Intended Audience :: Developers
Classifier: License :: OSI Approved :: BSD License
Classifier: Programming Language :: Python
Classifier: Programming Language :: Python :: 3
Classifier: Programming Language :: Python :: 3 :: Only
Classifier: Programming Language :: Python :: 3.8
Classifier: Programming Language :: Python :: 3.9
Classifier: Topic :: Software Development :: Libraries
Requires-Dist: pillow
Requires-Dist: requests
Requires-Dist: pysvg-py3
Requires-Dist: djangorestframework
